<?xml version="1.0" ?>
<aws:UrlInfoResponse xmlns:aws="http://awis.amazonaws.com/doc/2005-10-05">
  <aws:Response xmlns:aws="http://awis.amazonaws.com/doc/2005-07-11">
    <aws:OperationRequest>
      <aws:RequestId>98ded117-15c5-11e8-8df4-a9ea73e7c57d</aws:RequestId>
    </aws:OperationRequest>
    <aws:UrlInfoResult>
      <aws:Alexa>
        <aws:Request>
          <aws:Arguments>
            <aws:Argument>
              <aws:Name>url</aws:Name>
              <aws:Value>walmart.com</aws:Value>
            </aws:Argument>
            <aws:Argument>
              <aws:Name>responsegroup</aws:Name>
              <aws:Value>Categories,Rank,RankByCountry,UsageStats,AdultContent,Speed,Language,OwnedDomains,LinksInCount,SiteData,RelatedLinks</aws:Value>
            </aws:Argument>
          </aws:Arguments>
        </aws:Request>
        <aws:ContentData>
          <aws:DataUrl type="canonical">walmart.com</aws:DataUrl>
          <aws:SiteData>
            <aws:Title>Wal-Mart Online</aws:Title>
            <aws:Description>Provides customers with on-line shopping of wide range of inventory items. Retail, clothing, recreational and home products available.</aws:Description>
            <aws:OnlineSince>23-Feb-1995</aws:OnlineSince>
          </aws:SiteData>
          <aws:Speed>
            <aws:MedianLoadTime>3398</aws:MedianLoadTime>
            <aws:Percentile>20</aws:Percentile>
          </aws:Speed>
          <aws:AdultContent>no</aws:AdultContent>
          <aws:Language>
            <aws:Locale>en</aws:Locale>
          </aws:Language>
          <aws:LinksInCount>40247</aws:LinksInCount>
          <aws:OwnedDomains/>
        </aws:ContentData>
        <aws:Related>
          <aws:DataUrl type="canonical">walmart.com</aws:DataUrl>
          <aws:RelatedLinks>
            <aws:RelatedLink>
              <aws:DataUrl type="canonical">www3.jcpenney.com/</aws:DataUrl>
              <aws:NavigableUrl>http://www3.jcpenney.com/</aws:NavigableUrl>
              <aws:Title>JCPenney</aws:Title>
            </aws:RelatedLink>
            <aws:RelatedLink>
              <aws:DataUrl type="canonical">www.zales.com/</aws:DataUrl>
              <aws:NavigableUrl>http://www.zales.com/</aws:NavigableUrl>
              <aws:Title>Zales</aws:Title>
            </aws:RelatedLink>
            <aws:RelatedLink>
              <aws:DataUrl type="canonical">www.yahoo.com/</aws:DataUrl>
              <aws:NavigableUrl>http://www.yahoo.com/</aws:NavigableUrl>
              <aws:Title>Yahoo!</aws:Title>
            </aws:RelatedLink>
            <aws:RelatedLink>
              <aws:DataUrl type="canonical">www.walgreens.com/</aws:DataUrl>
              <aws:NavigableUrl>http://www.walgreens.com/</aws:NavigableUrl>
              <aws:Title>Walgreens</aws:Title>
            </aws:RelatedLink>
            <aws:RelatedLink>
              <aws:DataUrl type="canonical">www.victoriassecret.com/</aws:DataUrl>
              <aws:NavigableUrl>http://www.victoriassecret.com/</aws:NavigableUrl>
              <aws:Title>Victoriassecret.com: The Official Site Of Victoria's Secret</aws:Title>
            </aws:RelatedLink>
            <aws:RelatedLink>
              <aws:DataUrl type="canonical">www.valuecity.com/</aws:DataUrl>
              <aws:NavigableUrl>http://www.valuecity.com/</aws:NavigableUrl>
              <aws:Title>Value City Department Stores</aws:Title>
            </aws:RelatedLink>
            <aws:RelatedLink>
              <aws:DataUrl type="canonical">www.ups.com/</aws:DataUrl>
              <aws:NavigableUrl>http://www.ups.com/</aws:NavigableUrl>
              <aws:Title>Ups: Ups</aws:Title>
            </aws:RelatedLink>
            <aws:RelatedLink>
              <aws:DataUrl type="canonical">www.toysrus.com/</aws:DataUrl>
              <aws:NavigableUrl>http://www.toysrus.com/</aws:NavigableUrl>
              <aws:Title>Toys 'R Us</aws:Title>
            </aws:RelatedLink>
            <aws:RelatedLink>
              <aws:DataUrl type="canonical">www.techbargains.com/</aws:DataUrl>
              <aws:NavigableUrl>http://www.techbargains.com/</aws:NavigableUrl>
              <aws:Title>techbargains.com</aws:Title>
            </aws:RelatedLink>
            <aws:RelatedLink>
              <aws:DataUrl type="canonical">www.target.com/</aws:DataUrl>
              <aws:NavigableUrl>http://www.target.com/</aws:NavigableUrl>
              <aws:Title>Target</aws:Title>
            </aws:RelatedLink>
            <aws:RelatedLink>
              <aws:DataUrl type="canonical">walmart.inserts2online.com/</aws:DataUrl>
              <aws:NavigableUrl>http://walmart.inserts2online.com/</aws:NavigableUrl>
              <aws:Title>walmart.inserts2online.com/</aws:Title>
            </aws:RelatedLink>
          </aws:RelatedLinks>
          <aws:Categories>
            <aws:CategoryData>
              <aws:Title>General Merchandise/Major Retailers</aws:Title>
              <aws:AbsolutePath>Top/Shopping/General_Merchandise/Major_Retailers</aws:AbsolutePath>
            </aws:CategoryData>
            <aws:CategoryData>
              <aws:Title>Bentonville/Business and Economy</aws:Title>
              <aws:AbsolutePath>Top/Regional/North_America/United_States/Arkansas/Localities/B/Bentonville/Business_and_Economy</aws:AbsolutePath>
            </aws:CategoryData>
          </aws:Categories>
        </aws:Related>
        <aws:TrafficData>
          <aws:DataUrl type="canonical">walmart.com</aws:DataUrl>
          <aws:Rank>168</aws:Rank>
          <aws:RankByCountry>
            <aws:Country Code="IN">
              <aws:Rank>2449</aws:Rank>
              <aws:Contribution>
                <aws:PageViews>0.4%</aws:PageViews>
                <aws:Users>0.8%</aws:Users>
              </aws:Contribution>
            </aws:Country>
            <aws:Country Code="TW">
              <aws:Rank>555</aws:Rank>
              <aws:Contribution>
                <aws:PageViews>0.9%</aws:PageViews>
                <aws:Users>0.7%</aws:Users>
              </aws:Contribution>
            </aws:Country>
            <aws:Country Code="US">
              <aws:Rank>46</aws:Rank>
              <aws:Contribution>
                <aws:PageViews>79.5%</aws:PageViews>
                <aws:Users>80.9%</aws:Users>
              </aws:Contribution>
            </aws:Country>
            <aws:Country Code="KR">
              <aws:Rank>230</aws:Rank>
              <aws:Contribution>
                <aws:PageViews>3.1%</aws:PageViews>
                <aws:Users>2.2%</aws:Users>
              </aws:Contribution>
            </aws:Country>
            <aws:Country Code="CA">
              <aws:Rank>302</aws:Rank>
              <aws:Contribution>
                <aws:PageViews>1.0%</aws:PageViews>
                <aws:Users>1.8%</aws:Users>
              </aws:Contribution>
            </aws:Country>
            <aws:Country Code="JP">
              <aws:Rank>237</aws:Rank>
              <aws:Contribution>
                <aws:PageViews>8.6%</aws:PageViews>
                <aws:Users>6.3%</aws:Users>
              </aws:Contribution>
            </aws:Country>
            <aws:Country Code="CN">
              <aws:Rank>2791</aws:Rank>
              <aws:Contribution>
                <aws:PageViews>1.0%</aws:PageViews>
                <aws:Users>0.9%</aws:Users>
              </aws:Contribution>
            </aws:Country>
            <aws:Country Code="O">
              <aws:Rank/>
              <aws:Contribution>
                <aws:PageViews>5.5%</aws:PageViews>
                <aws:Users>6.4%</aws:Users>
              </aws:Contribution>
            </aws:Country>
          </aws:RankByCountry>
          <aws:UsageStatistics>
            <aws:UsageStatistic>
              <aws:TimeRange>
                <aws:Months>3</aws:Months>
              </aws:TimeRange>
              <aws:Rank>
                <aws:Value>168</aws:Value>
                <aws:Delta>-23</aws:Delta>
              </aws:Rank>
              <aws:Reach>
                <aws:Rank>
                  <aws:Value>168</aws:Value>
                  <aws:Delta>-23</aws:Delta>
                </aws:Rank>
                <aws:PerMillion>
                  <aws:Value>4,021</aws:Value>
                  <aws:Delta>+13.8%</aws:Delta>
                </aws:PerMillion>
              </aws:Reach>
              <aws:PageViews>
                <aws:PerMillion>
                  <aws:Value>396.2</aws:Value>
                  <aws:Delta>+15.1%</aws:Delta>
                </aws:PerMillion>
                <aws:Rank>
                  <aws:Value>181</aws:Value>
                  <aws:Delta>-41</aws:Delta>
                </aws:Rank>
                <aws:PerUser>
                  <aws:Value>3.92</aws:Value>
                  <aws:Delta>+1%</aws:Delta>
                </aws:PerUser>
              </aws:PageViews>
            </aws:UsageStatistic>
            <aws:UsageStatistic>
              <aws:TimeRange>
                <aws:Months>1</aws:Months>
              </aws:TimeRange>
              <aws:Rank>
                <aws:Value>217</aws:Value>
                <aws:Delta>+36</aws:Delta>
              </aws:Rank>
              <aws:Reach>
                <aws:Rank>
                  <aws:Value>223</aws:Value>
                  <aws:Delta>+43</aws:Delta>
                </aws:Rank>
                <aws:PerMillion>
                  <aws:Value>3,140</aws:Value>
                  <aws:Delta>-13.19%</aws:Delta>
                </aws:PerMillion>
              </aws:Reach>
              <aws:PageViews>
                <aws:PerMillion>
                  <aws:Value>294.7</aws:Value>
                  <aws:Delta>-17.28%</aws:Delta>
                </aws:PerMillion>
                <aws:Rank>
                  <aws:Value>250</aws:Value>
                  <aws:Delta>45</aws:Delta>
                </aws:Rank>
                <aws:PerUser>
                  <aws:Value>3.65</aws:Value>
                  <aws:Delta>-4.70%</aws:Delta>
                </aws:PerUser>
              </aws:PageViews>
            </aws:UsageStatistic>
            <aws:UsageStatistic>
              <aws:TimeRange>
                <aws:Days>7</aws:Days>
              </aws:TimeRange>
              <aws:Rank>
                <aws:Value>205</aws:Value>
                <aws:Delta>-11</aws:Delta>
              </aws:Rank>
              <aws:Reach>
                <aws:Rank>
                  <aws:Value>203</aws:Value>
                  <aws:Delta>-21</aws:Delta>
                </aws:Rank>
                <aws:PerMillion>
                  <aws:Value>3,200</aws:Value>
                  <aws:Delta>+3%</aws:Delta>
                </aws:PerMillion>
              </aws:Reach>
              <aws:PageViews>
                <aws:PerMillion>
                  <aws:Value>302</aws:Value>
                  <aws:Delta>+1.9%</aws:Delta>
                </aws:PerMillion>
                <aws:Rank>
                  <aws:Value>241</aws:Value>
                  <aws:Delta>-12</aws:Delta>
                </aws:Rank>
                <aws:PerUser>
                  <aws:Value>3.61</aws:Value>
                  <aws:Delta>-1.10%</aws:Delta>
                </aws:PerUser>
              </aws:PageViews>
            </aws:UsageStatistic>
            <aws:UsageStatistic>
              <aws:TimeRange>
                <aws:Days>1</aws:Days>
              </aws:TimeRange>
              <aws:Rank>
                <aws:Value>181</aws:Value>
                <aws:Delta>-8</aws:Delta>
              </aws:Rank>
              <aws:Reach>
                <aws:Rank>
                  <aws:Value>191</aws:Value>
                  <aws:Delta>-3</aws:Delta>
                </aws:Rank>
                <aws:PerMillion>
                  <aws:Value>3,570</aws:Value>
                  <aws:Delta>+5%</aws:Delta>
                </aws:PerMillion>
              </aws:Reach>
              <aws:PageViews>
                <aws:PerMillion>
                  <aws:Value>348</aws:Value>
                  <aws:Delta>+3%</aws:Delta>
                </aws:PerMillion>
                <aws:Rank>
                  <aws:Value>216</aws:Value>
                  <aws:Delta>-1</aws:Delta>
                </aws:Rank>
                <aws:PerUser>
                  <aws:Value>3.62</aws:Value>
                  <aws:Delta>-1.36%</aws:Delta>
                </aws:PerUser>
              </aws:PageViews>
            </aws:UsageStatistic>
          </aws:UsageStatistics>
          <aws:ContributingSubdomains>
            <aws:ContributingSubdomain>
              <aws:DataUrl>walmart.com</aws:DataUrl>
              <aws:TimeRange>
                <aws:Months>1</aws:Months>
              </aws:TimeRange>
              <aws:Reach>
                <aws:Percentage>95.95%</aws:Percentage>
              </aws:Reach>
              <aws:PageViews>
                <aws:Percentage>89.99%</aws:Percentage>
                <aws:PerUser>3.42</aws:PerUser>
              </aws:PageViews>
            </aws:ContributingSubdomain>
            <aws:ContributingSubdomain>
              <aws:DataUrl>photos3.walmart.com</aws:DataUrl>
              <aws:TimeRange>
                <aws:Months>1</aws:Months>
              </aws:TimeRange>
              <aws:Reach>
                <aws:Percentage>2.25%</aws:Percentage>
              </aws:Reach>
              <aws:PageViews>
                <aws:Percentage>1.74%</aws:Percentage>
                <aws:PerUser>2.8</aws:PerUser>
              </aws:PageViews>
            </aws:ContributingSubdomain>
            <aws:ContributingSubdomain>
              <aws:DataUrl>grocery.walmart.com</aws:DataUrl>
              <aws:TimeRange>
                <aws:Months>1</aws:Months>
              </aws:TimeRange>
              <aws:Reach>
                <aws:Percentage>2.38%</aws:Percentage>
              </aws:Reach>
              <aws:PageViews>
                <aws:Percentage>1.45%</aws:Percentage>
                <aws:PerUser>2.22</aws:PerUser>
              </aws:PageViews>
            </aws:ContributingSubdomain>
            <aws:ContributingSubdomain>
              <aws:DataUrl>corporate.walmart.com</aws:DataUrl>
              <aws:TimeRange>
                <aws:Months>1</aws:Months>
              </aws:TimeRange>
              <aws:Reach>
                <aws:Percentage>3.33%</aws:Percentage>
              </aws:Reach>
              <aws:PageViews>
                <aws:Percentage>1.05%</aws:Percentage>
                <aws:PerUser>1.1</aws:PerUser>
              </aws:PageViews>
            </aws:ContributingSubdomain>
            <aws:ContributingSubdomain>
              <aws:DataUrl>seller.walmart.com</aws:DataUrl>
              <aws:TimeRange>
                <aws:Months>1</aws:Months>
              </aws:TimeRange>
              <aws:Reach>
                <aws:Percentage>1.07%</aws:Percentage>
              </aws:Reach>
              <aws:PageViews>
                <aws:Percentage>0.86%</aws:Percentage>
                <aws:PerUser>2.9</aws:PerUser>
              </aws:PageViews>
            </aws:ContributingSubdomain>
            <aws:ContributingSubdomain>
              <aws:DataUrl>help.walmart.com</aws:DataUrl>
              <aws:TimeRange>
                <aws:Months>1</aws:Months>
              </aws:TimeRange>
              <aws:Reach>
                <aws:Percentage>1.84%</aws:Percentage>
              </aws:Reach>
              <aws:PageViews>
                <aws:Percentage>0.81%</aws:Percentage>
                <aws:PerUser>1.6</aws:PerUser>
              </aws:PageViews>
            </aws:ContributingSubdomain>
            <aws:ContributingSubdomain>
              <aws:DataUrl>careers.walmart.com</aws:DataUrl>
              <aws:TimeRange>
                <aws:Months>1</aws:Months>
              </aws:TimeRange>
              <aws:Reach>
                <aws:Percentage>0.80%</aws:Percentage>
              </aws:Reach>
              <aws:PageViews>
                <aws:Percentage>0.68%</aws:Percentage>
                <aws:PerUser>3.1</aws:PerUser>
              </aws:PageViews>
            </aws:ContributingSubdomain>
            <aws:ContributingSubdomain>
              <aws:DataUrl>tracking01.walmart.com</aws:DataUrl>
              <aws:TimeRange>
                <aws:Months>1</aws:Months>
              </aws:TimeRange>
              <aws:Reach>
                <aws:Percentage>1.08%</aws:Percentage>
              </aws:Reach>
              <aws:PageViews>
                <aws:Percentage>0.43%</aws:Percentage>
                <aws:PerUser>1.4</aws:PerUser>
              </aws:PageViews>
            </aws:ContributingSubdomain>
            <aws:ContributingSubdomain>
              <aws:DataUrl>partner.walmart.com</aws:DataUrl>
              <aws:TimeRange>
                <aws:Months>1</aws:Months>
              </aws:TimeRange>
              <aws:Reach>
                <aws:Percentage>1.02%</aws:Percentage>
              </aws:Reach>
              <aws:PageViews>
                <aws:Percentage>0.40%</aws:Percentage>
                <aws:PerUser>1.4</aws:PerUser>
              </aws:PageViews>
            </aws:ContributingSubdomain>
            <aws:ContributingSubdomain>
              <aws:DataUrl>savingscatcher.walmart.com</aws:DataUrl>
              <aws:TimeRange>
                <aws:Months>1</aws:Months>
              </aws:TimeRange>
              <aws:Reach>
                <aws:Percentage>0.69%</aws:Percentage>
              </aws:Reach>
              <aws:PageViews>
                <aws:Percentage>0.36%</aws:Percentage>
                <aws:PerUser>1.9</aws:PerUser>
              </aws:PageViews>
            </aws:ContributingSubdomain>
            <aws:ContributingSubdomain>
              <aws:DataUrl>stock.walmart.com</aws:DataUrl>
              <aws:TimeRange>
                <aws:Months>1</aws:Months>
              </aws:TimeRange>
              <aws:Reach>
                <aws:Percentage>0.66%</aws:Percentage>
              </aws:Reach>
              <aws:PageViews>
                <aws:Percentage>0.20%</aws:Percentage>
                <aws:PerUser>1.1</aws:PerUser>
              </aws:PageViews>
            </aws:ContributingSubdomain>
            <aws:ContributingSubdomain>
              <aws:DataUrl>prod.walmart.com</aws:DataUrl>
              <aws:TimeRange>
                <aws:Months>1</aws:Months>
              </aws:TimeRange>
              <aws:Reach>
                <aws:Percentage>0.09%</aws:Percentage>
              </aws:Reach>
              <aws:PageViews>
                <aws:Percentage>0.16%</aws:Percentage>
                <aws:PerUser>6.2</aws:PerUser>
              </aws:PageViews>
            </aws:ContributingSubdomain>
            <aws:ContributingSubdomain>
              <aws:DataUrl>marketplace.walmart.com</aws:DataUrl>
              <aws:TimeRange>
                <aws:Months>1</aws:Months>
              </aws:TimeRange>
              <aws:Reach>
                <aws:Percentage>0.35%</aws:Percentage>
              </aws:Reach>
              <aws:PageViews>
                <aws:Percentage>0.16%</aws:Percentage>
                <aws:PerUser>1.6</aws:PerUser>
              </aws:PageViews>
            </aws:ContributingSubdomain>
            <aws:ContributingSubdomain>
              <aws:DataUrl>survey.walmart.com</aws:DataUrl>
              <aws:TimeRange>
                <aws:Months>1</aws:Months>
              </aws:TimeRange>
              <aws:Reach>
                <aws:Percentage>0.16%</aws:Percentage>
              </aws:Reach>
              <aws:PageViews>
                <aws:Percentage>0.15%</aws:Percentage>
                <aws:PerUser>3.5</aws:PerUser>
              </aws:PageViews>
            </aws:ContributingSubdomain>
            <aws:ContributingSubdomain>
              <aws:DataUrl>giving.walmart.com</aws:DataUrl>
              <aws:TimeRange>
                <aws:Months>1</aws:Months>
              </aws:TimeRange>
              <aws:Reach>
                <aws:Percentage>0.45%</aws:Percentage>
              </aws:Reach>
              <aws:PageViews>
                <aws:Percentage>0.15%</aws:Percentage>
                <aws:PerUser>1.2</aws:PerUser>
              </aws:PageViews>
            </aws:ContributingSubdomain>
            <aws:ContributingSubdomain>
              <aws:DataUrl>gecgithub01.walmart.com</aws:DataUrl>
              <aws:TimeRange>
                <aws:Months>1</aws:Months>
              </aws:TimeRange>
              <aws:Reach>
                <aws:Percentage>0.08%</aws:Percentage>
              </aws:Reach>
              <aws:PageViews>
                <aws:Percentage>0.12%</aws:Percentage>
                <aws:PerUser>5.8</aws:PerUser>
              </aws:PageViews>
            </aws:ContributingSubdomain>
            <aws:ContributingSubdomain>
              <aws:DataUrl>supplier.walmart.com</aws:DataUrl>
              <aws:TimeRange>
                <aws:Months>1</aws:Months>
              </aws:TimeRange>
              <aws:Reach>
                <aws:Percentage>0.16%</aws:Percentage>
              </aws:Reach>
              <aws:PageViews>
                <aws:Percentage>0.12%</aws:Percentage>
                <aws:PerUser>2.8</aws:PerUser>
              </aws:PageViews>
            </aws:ContributingSubdomain>
            <aws:ContributingSubdomain>
              <aws:DataUrl>jira.walmart.com</aws:DataUrl>
              <aws:TimeRange>
                <aws:Months>1</aws:Months>
              </aws:TimeRange>
              <aws:Reach>
                <aws:Percentage>0.08%</aws:Percentage>
              </aws:Reach>
              <aws:PageViews>
                <aws:Percentage>0.12%</aws:Percentage>
                <aws:PerUser>5.2</aws:PerUser>
              </aws:PageViews>
            </aws:ContributingSubdomain>
            <aws:ContributingSubdomain>
              <aws:DataUrl>confluence.walmart.com</aws:DataUrl>
              <aws:TimeRange>
                <aws:Months>1</aws:Months>
              </aws:TimeRange>
              <aws:Reach>
                <aws:Percentage>0.09%</aws:Percentage>
              </aws:Reach>
              <aws:PageViews>
                <aws:Percentage>0.11%</aws:Percentage>
                <aws:PerUser>4.4</aws:PerUser>
              </aws:PageViews>
            </aws:ContributingSubdomain>
            <aws:ContributingSubdomain>
              <aws:DataUrl>track.walmart.com</aws:DataUrl>
              <aws:TimeRange>
                <aws:Months>1</aws:Months>
              </aws:TimeRange>
              <aws:Reach>
                <aws:Percentage>0.26%</aws:Percentage>
              </aws:Reach>
              <aws:PageViews>
                <aws:Percentage>0.08%</aws:Percentage>
                <aws:PerUser>1.2</aws:PerUser>
              </aws:PageViews>
            </aws:ContributingSubdomain>
            <aws:ContributingSubdomain>
              <aws:DataUrl>ci.walmart.com</aws:DataUrl>
              <aws:TimeRange>
                <aws:Months>1</aws:Months>
              </aws:TimeRange>
              <aws:Reach>
                <aws:Percentage>0.02%</aws:Percentage>
              </aws:Reach>
              <aws:PageViews>
                <aws:Percentage>0.07%</aws:Percentage>
                <aws:PerUser>16</aws:PerUser>
              </aws:PageViews>
            </aws:ContributingSubdomain>
            <aws:ContributingSubdomain>
              <aws:DataUrl>beautybox.walmart.com</aws:DataUrl>
              <aws:TimeRange>
                <aws:Months>1</aws:Months>
              </aws:TimeRange>
              <aws:Reach>
                <aws:Percentage>0.10%</aws:Percentage>
              </aws:Reach>
              <aws:PageViews>
                <aws:Percentage>0.06%</aws:Percentage>
                <aws:PerUser>2.3</aws:PerUser>
              </aws:PageViews>
            </aws:ContributingSubdomain>
            <aws:ContributingSubdomain>
              <aws:DataUrl>coupons.walmart.com</aws:DataUrl>
              <aws:TimeRange>
                <aws:Months>1</aws:Months>
              </aws:TimeRange>
              <aws:Reach>
                <aws:Percentage>0.14%</aws:Percentage>
              </aws:Reach>
              <aws:PageViews>
                <aws:Percentage>0.06%</aws:Percentage>
                <aws:PerUser>1.7</aws:PerUser>
              </aws:PageViews>
            </aws:ContributingSubdomain>
            <aws:ContributingSubdomain>
              <aws:DataUrl>instantcredit.walmart.com</aws:DataUrl>
              <aws:TimeRange>
                <aws:Months>1</aws:Months>
              </aws:TimeRange>
              <aws:Reach>
                <aws:Percentage>0.12%</aws:Percentage>
              </aws:Reach>
              <aws:PageViews>
                <aws:Percentage>0.06%</aws:Percentage>
                <aws:PerUser>1.8</aws:PerUser>
              </aws:PageViews>
            </aws:ContributingSubdomain>
            <aws:ContributingSubdomain>
              <aws:DataUrl>affiliates.walmart.com</aws:DataUrl>
              <aws:TimeRange>
                <aws:Months>1</aws:Months>
              </aws:TimeRange>
              <aws:Reach>
                <aws:Percentage>0.13%</aws:Percentage>
              </aws:Reach>
              <aws:PageViews>
                <aws:Percentage>0.06%</aws:Percentage>
                <aws:PerUser>1.6</aws:PerUser>
              </aws:PageViews>
            </aws:ContributingSubdomain>
            <aws:ContributingSubdomain>
              <aws:DataUrl>OTHER</aws:DataUrl>
              <aws:TimeRange>
                <aws:Months>1</aws:Months>
              </aws:TimeRange>
              <aws:Reach>
                <aws:Percentage>0</aws:Percentage>
              </aws:Reach>
              <aws:PageViews>
                <aws:Percentage>0.57%</aws:Percentage>
                <aws:PerUser>0</aws:PerUser>
              </aws:PageViews>
            </aws:ContributingSubdomain>
          </aws:ContributingSubdomains>
        </aws:TrafficData>
      </aws:Alexa>
    </aws:UrlInfoResult>
    <aws:ResponseStatus xmlns:aws="http://alexa.amazonaws.com/doc/2005-10-05/">
      <aws:StatusCode>Success</aws:StatusCode>
    </aws:ResponseStatus>
  </aws:Response>
</aws:UrlInfoResponse>
