<?xml version="1.0" ?>
<aws:UrlInfoResponse xmlns:aws="http://awis.amazonaws.com/doc/2005-10-05">
  <aws:Response xmlns:aws="http://awis.amazonaws.com/doc/2005-07-11">
    <aws:OperationRequest>
      <aws:RequestId>96726571-15c5-11e8-b1f4-59e8c3a84043</aws:RequestId>
    </aws:OperationRequest>
    <aws:UrlInfoResult>
      <aws:Alexa>
        <aws:Request>
          <aws:Arguments>
            <aws:Argument>
              <aws:Name>url</aws:Name>
              <aws:Value>hulu.com</aws:Value>
            </aws:Argument>
            <aws:Argument>
              <aws:Name>responsegroup</aws:Name>
              <aws:Value>Categories,Rank,RankByCountry,UsageStats,AdultContent,Speed,Language,OwnedDomains,LinksInCount,SiteData,RelatedLinks</aws:Value>
            </aws:Argument>
          </aws:Arguments>
        </aws:Request>
        <aws:ContentData>
          <aws:DataUrl type="canonical">hulu.com</aws:DataUrl>
          <aws:SiteData>
            <aws:Title>Hulu</aws:Title>
            <aws:Description>Ad-supported streaming television shows and movies, including some in high definition.</aws:Description>
            <aws:OnlineSince>21-Feb-1997</aws:OnlineSince>
          </aws:SiteData>
          <aws:Speed>
            <aws:MedianLoadTime>3018</aws:MedianLoadTime>
            <aws:Percentile>25</aws:Percentile>
          </aws:Speed>
          <aws:AdultContent>no</aws:AdultContent>
          <aws:Language>
            <aws:Locale>en</aws:Locale>
          </aws:Language>
          <aws:LinksInCount>21085</aws:LinksInCount>
          <aws:OwnedDomains/>
        </aws:ContentData>
        <aws:Related>
          <aws:DataUrl type="canonical">hulu.com</aws:DataUrl>
          <aws:RelatedLinks>
            <aws:RelatedLink>
              <aws:DataUrl type="canonical">ycombinator.com/</aws:DataUrl>
              <aws:NavigableUrl>http://ycombinator.com/</aws:NavigableUrl>
              <aws:Title>Y Combinator</aws:Title>
            </aws:RelatedLink>
            <aws:RelatedLink>
              <aws:DataUrl type="canonical">xy7.com/</aws:DataUrl>
              <aws:NavigableUrl>http://xy7.com/</aws:NavigableUrl>
              <aws:Title>Xy7.com</aws:Title>
            </aws:RelatedLink>
            <aws:RelatedLink>
              <aws:DataUrl type="canonical">xkcd.com/</aws:DataUrl>
              <aws:NavigableUrl>http://xkcd.com/</aws:NavigableUrl>
              <aws:Title>xkcd</aws:Title>
            </aws:RelatedLink>
            <aws:RelatedLink>
              <aws:DataUrl type="canonical">www.zuula.com/</aws:DataUrl>
              <aws:NavigableUrl>http://www.zuula.com/</aws:NavigableUrl>
              <aws:Title>Zuula Search</aws:Title>
            </aws:RelatedLink>
            <aws:RelatedLink>
              <aws:DataUrl type="canonical">www.zazzle.com/</aws:DataUrl>
              <aws:NavigableUrl>http://www.zazzle.com/</aws:NavigableUrl>
              <aws:Title>Zazzle, Inc.</aws:Title>
            </aws:RelatedLink>
            <aws:RelatedLink>
              <aws:DataUrl type="canonical">www.zap2it.com/</aws:DataUrl>
              <aws:NavigableUrl>http://www.zap2it.com/</aws:NavigableUrl>
              <aws:Title>Zap2it.com</aws:Title>
            </aws:RelatedLink>
            <aws:RelatedLink>
              <aws:DataUrl type="canonical">www.yuku.com/</aws:DataUrl>
              <aws:NavigableUrl>http://www.yuku.com/</aws:NavigableUrl>
              <aws:Title>Yuku | Social network, forum, chat and more</aws:Title>
            </aws:RelatedLink>
            <aws:RelatedLink>
              <aws:DataUrl type="canonical">www.youtube.com/</aws:DataUrl>
              <aws:NavigableUrl>http://www.youtube.com/</aws:NavigableUrl>
              <aws:Title>YouTube</aws:Title>
            </aws:RelatedLink>
            <aws:RelatedLink>
              <aws:DataUrl type="canonical">www.yelp.com/</aws:DataUrl>
              <aws:NavigableUrl>http://www.yelp.com/</aws:NavigableUrl>
              <aws:Title>Yelp</aws:Title>
            </aws:RelatedLink>
            <aws:RelatedLink>
              <aws:DataUrl type="canonical">www.xsharex.info/</aws:DataUrl>
              <aws:NavigableUrl>http://www.xsharex.info/</aws:NavigableUrl>
              <aws:Title>Log In</aws:Title>
            </aws:RelatedLink>
          </aws:RelatedLinks>
          <aws:Categories>
            <aws:CategoryData>
              <aws:Title>Entertainment/Online Media</aws:Title>
              <aws:AbsolutePath>Top/Arts/Entertainment/Online_Media</aws:AbsolutePath>
            </aws:CategoryData>
            <aws:CategoryData>
              <aws:Title>Science Fiction and Fantasy/Sliders</aws:Title>
              <aws:AbsolutePath>Top/Arts/Television/Programs/Science_Fiction_and_Fantasy/S/Sliders</aws:AbsolutePath>
            </aws:CategoryData>
          </aws:Categories>
        </aws:Related>
        <aws:TrafficData>
          <aws:DataUrl type="canonical">hulu.com</aws:DataUrl>
          <aws:Rank>245</aws:Rank>
          <aws:RankByCountry>
            <aws:Country Code="US">
              <aws:Rank>40</aws:Rank>
              <aws:Contribution>
                <aws:PageViews>96.3%</aws:PageViews>
                <aws:Users>96.0%</aws:Users>
              </aws:Contribution>
            </aws:Country>
            <aws:Country Code="O">
              <aws:Rank/>
              <aws:Contribution>
                <aws:PageViews>3.7%</aws:PageViews>
                <aws:Users>4.0%</aws:Users>
              </aws:Contribution>
            </aws:Country>
          </aws:RankByCountry>
          <aws:UsageStatistics>
            <aws:UsageStatistic>
              <aws:TimeRange>
                <aws:Months>3</aws:Months>
              </aws:TimeRange>
              <aws:Rank>
                <aws:Value>245</aws:Value>
                <aws:Delta>-57</aws:Delta>
              </aws:Rank>
              <aws:Reach>
                <aws:Rank>
                  <aws:Value>206</aws:Value>
                  <aws:Delta>-37</aws:Delta>
                </aws:Rank>
                <aws:PerMillion>
                  <aws:Value>3,333</aws:Value>
                  <aws:Delta>+17.9%</aws:Delta>
                </aws:PerMillion>
              </aws:Reach>
              <aws:PageViews>
                <aws:PerMillion>
                  <aws:Value>168.9</aws:Value>
                  <aws:Delta>+21.8%</aws:Delta>
                </aws:PerMillion>
                <aws:Rank>
                  <aws:Value>408</aws:Value>
                  <aws:Delta>-83</aws:Delta>
                </aws:Rank>
                <aws:PerUser>
                  <aws:Value>2.02</aws:Value>
                  <aws:Delta>+3.6%</aws:Delta>
                </aws:PerUser>
              </aws:PageViews>
            </aws:UsageStatistic>
            <aws:UsageStatistic>
              <aws:TimeRange>
                <aws:Months>1</aws:Months>
              </aws:TimeRange>
              <aws:Rank>
                <aws:Value>234</aws:Value>
                <aws:Delta>-3</aws:Delta>
              </aws:Rank>
              <aws:Reach>
                <aws:Rank>
                  <aws:Value>205</aws:Value>
                  <aws:Delta>+2</aws:Delta>
                </aws:Rank>
                <aws:PerMillion>
                  <aws:Value>3,346</aws:Value>
                  <aws:Delta>-0.049%</aws:Delta>
                </aws:PerMillion>
              </aws:Reach>
              <aws:PageViews>
                <aws:PerMillion>
                  <aws:Value>178.2</aws:Value>
                  <aws:Delta>-2.23%</aws:Delta>
                </aws:PerMillion>
                <aws:Rank>
                  <aws:Value>390</aws:Value>
                  <aws:Delta>13</aws:Delta>
                </aws:Rank>
                <aws:PerUser>
                  <aws:Value>2.07</aws:Value>
                  <aws:Delta>-2.36%</aws:Delta>
                </aws:PerUser>
              </aws:PageViews>
            </aws:UsageStatistic>
            <aws:UsageStatistic>
              <aws:TimeRange>
                <aws:Days>7</aws:Days>
              </aws:TimeRange>
              <aws:Rank>
                <aws:Value>244</aws:Value>
                <aws:Delta>+15</aws:Delta>
              </aws:Rank>
              <aws:Reach>
                <aws:Rank>
                  <aws:Value>202</aws:Value>
                  <aws:Delta>+3</aws:Delta>
                </aws:Rank>
                <aws:PerMillion>
                  <aws:Value>3,200</aws:Value>
                  <aws:Delta>-5.921%</aws:Delta>
                </aws:PerMillion>
              </aws:Reach>
              <aws:PageViews>
                <aws:PerMillion>
                  <aws:Value>172</aws:Value>
                  <aws:Delta>-11.54%</aws:Delta>
                </aws:PerMillion>
                <aws:Rank>
                  <aws:Value>401</aws:Value>
                  <aws:Delta>38</aws:Delta>
                </aws:Rank>
                <aws:PerUser>
                  <aws:Value>2.05</aws:Value>
                  <aws:Delta>-5.963%</aws:Delta>
                </aws:PerUser>
              </aws:PageViews>
            </aws:UsageStatistic>
            <aws:UsageStatistic>
              <aws:TimeRange>
                <aws:Days>1</aws:Days>
              </aws:TimeRange>
              <aws:Rank>
                <aws:Value>212</aws:Value>
                <aws:Delta>+2</aws:Delta>
              </aws:Rank>
              <aws:Reach>
                <aws:Rank>
                  <aws:Value>180</aws:Value>
                  <aws:Delta>-1</aws:Delta>
                </aws:Rank>
                <aws:PerMillion>
                  <aws:Value>3,770</aws:Value>
                  <aws:Delta>+2%</aws:Delta>
                </aws:PerMillion>
              </aws:Reach>
              <aws:PageViews>
                <aws:PerMillion>
                  <aws:Value>214</aws:Value>
                  <aws:Delta>+5%</aws:Delta>
                </aws:PerMillion>
                <aws:Rank>
                  <aws:Value>349</aws:Value>
                  <aws:Delta>0</aws:Delta>
                </aws:Rank>
                <aws:PerUser>
                  <aws:Value>2.11</aws:Value>
                  <aws:Delta>+2%</aws:Delta>
                </aws:PerUser>
              </aws:PageViews>
            </aws:UsageStatistic>
          </aws:UsageStatistics>
          <aws:ContributingSubdomains>
            <aws:ContributingSubdomain>
              <aws:DataUrl>hulu.com</aws:DataUrl>
              <aws:TimeRange>
                <aws:Months>1</aws:Months>
              </aws:TimeRange>
              <aws:Reach>
                <aws:Percentage>97.82%</aws:Percentage>
              </aws:Reach>
              <aws:PageViews>
                <aws:Percentage>83.03%</aws:Percentage>
                <aws:PerUser>1.76</aws:PerUser>
              </aws:PageViews>
            </aws:ContributingSubdomain>
            <aws:ContributingSubdomain>
              <aws:DataUrl>secure.hulu.com</aws:DataUrl>
              <aws:TimeRange>
                <aws:Months>1</aws:Months>
              </aws:TimeRange>
              <aws:Reach>
                <aws:Percentage>8.57%</aws:Percentage>
              </aws:Reach>
              <aws:PageViews>
                <aws:Percentage>5.71%</aws:Percentage>
                <aws:PerUser>1.38</aws:PerUser>
              </aws:PageViews>
            </aws:ContributingSubdomain>
            <aws:ContributingSubdomain>
              <aws:DataUrl>signup.hulu.com</aws:DataUrl>
              <aws:TimeRange>
                <aws:Months>1</aws:Months>
              </aws:TimeRange>
              <aws:Reach>
                <aws:Percentage>4.36%</aws:Percentage>
              </aws:Reach>
              <aws:PageViews>
                <aws:Percentage>3.07%</aws:Percentage>
                <aws:PerUser>1.46</aws:PerUser>
              </aws:PageViews>
            </aws:ContributingSubdomain>
            <aws:ContributingSubdomain>
              <aws:DataUrl>auth.hulu.com</aws:DataUrl>
              <aws:TimeRange>
                <aws:Months>1</aws:Months>
              </aws:TimeRange>
              <aws:Reach>
                <aws:Percentage>5.73%</aws:Percentage>
              </aws:Reach>
              <aws:PageViews>
                <aws:Percentage>2.87%</aws:Percentage>
                <aws:PerUser>1.04</aws:PerUser>
              </aws:PageViews>
            </aws:ContributingSubdomain>
            <aws:ContributingSubdomain>
              <aws:DataUrl>help.hulu.com</aws:DataUrl>
              <aws:TimeRange>
                <aws:Months>1</aws:Months>
              </aws:TimeRange>
              <aws:Reach>
                <aws:Percentage>3.00%</aws:Percentage>
              </aws:Reach>
              <aws:PageViews>
                <aws:Percentage>2.78%</aws:Percentage>
                <aws:PerUser>1.92</aws:PerUser>
              </aws:PageViews>
            </aws:ContributingSubdomain>
            <aws:ContributingSubdomain>
              <aws:DataUrl>beta.hulu.com</aws:DataUrl>
              <aws:TimeRange>
                <aws:Months>1</aws:Months>
              </aws:TimeRange>
              <aws:Reach>
                <aws:Percentage>2.25%</aws:Percentage>
              </aws:Reach>
              <aws:PageViews>
                <aws:Percentage>1.70%</aws:Percentage>
                <aws:PerUser>1.57</aws:PerUser>
              </aws:PageViews>
            </aws:ContributingSubdomain>
            <aws:ContributingSubdomain>
              <aws:DataUrl>prod.hulu.com</aws:DataUrl>
              <aws:TimeRange>
                <aws:Months>1</aws:Months>
              </aws:TimeRange>
              <aws:Reach>
                <aws:Percentage>0.10%</aws:Percentage>
              </aws:Reach>
              <aws:PageViews>
                <aws:Percentage>0.29%</aws:Percentage>
                <aws:PerUser>6.4</aws:PerUser>
              </aws:PageViews>
            </aws:ContributingSubdomain>
            <aws:ContributingSubdomain>
              <aws:DataUrl>login.hulu.com</aws:DataUrl>
              <aws:TimeRange>
                <aws:Months>1</aws:Months>
              </aws:TimeRange>
              <aws:Reach>
                <aws:Percentage>0.13%</aws:Percentage>
              </aws:Reach>
              <aws:PageViews>
                <aws:Percentage>0.17%</aws:Percentage>
                <aws:PerUser>2.7</aws:PerUser>
              </aws:PageViews>
            </aws:ContributingSubdomain>
            <aws:ContributingSubdomain>
              <aws:DataUrl>jira.hulu.com</aws:DataUrl>
              <aws:TimeRange>
                <aws:Months>1</aws:Months>
              </aws:TimeRange>
              <aws:Reach>
                <aws:Percentage>0.06%</aws:Percentage>
              </aws:Reach>
              <aws:PageViews>
                <aws:Percentage>0.11%</aws:Percentage>
                <aws:PerUser>3.5</aws:PerUser>
              </aws:PageViews>
            </aws:ContributingSubdomain>
            <aws:ContributingSubdomain>
              <aws:DataUrl>huluverse.hulu.com</aws:DataUrl>
              <aws:TimeRange>
                <aws:Months>1</aws:Months>
              </aws:TimeRange>
              <aws:Reach>
                <aws:Percentage>0.07%</aws:Percentage>
              </aws:Reach>
              <aws:PageViews>
                <aws:Percentage>0.10%</aws:Percentage>
                <aws:PerUser>3.0</aws:PerUser>
              </aws:PageViews>
            </aws:ContributingSubdomain>
            <aws:ContributingSubdomain>
              <aws:DataUrl>wiki.hulu.com</aws:DataUrl>
              <aws:TimeRange>
                <aws:Months>1</aws:Months>
              </aws:TimeRange>
              <aws:Reach>
                <aws:Percentage>0.04%</aws:Percentage>
              </aws:Reach>
              <aws:PageViews>
                <aws:Percentage>0.06%</aws:Percentage>
                <aws:PerUser>3.3</aws:PerUser>
              </aws:PageViews>
            </aws:ContributingSubdomain>
            <aws:ContributingSubdomain>
              <aws:DataUrl>OTHER</aws:DataUrl>
              <aws:TimeRange>
                <aws:Months>1</aws:Months>
              </aws:TimeRange>
              <aws:Reach>
                <aws:Percentage>0</aws:Percentage>
              </aws:Reach>
              <aws:PageViews>
                <aws:Percentage>0.12%</aws:Percentage>
                <aws:PerUser>0</aws:PerUser>
              </aws:PageViews>
            </aws:ContributingSubdomain>
          </aws:ContributingSubdomains>
        </aws:TrafficData>
      </aws:Alexa>
    </aws:UrlInfoResult>
    <aws:ResponseStatus xmlns:aws="http://alexa.amazonaws.com/doc/2005-10-05/">
      <aws:StatusCode>Success</aws:StatusCode>
    </aws:ResponseStatus>
  </aws:Response>
</aws:UrlInfoResponse>
